nonebot_plugin_guess_song-1.4.0.dist-info/METADATA
nonebot_plugin_guess_song-1.4.0.dist-info/WHEEL
nonebot_plugin_guess_song-1.4.0.dist-info/entry_points.txt
nonebot_plugin_guess_song-1.4.0.dist-info/licenses/LICENSE
nonebot_plugin_guess_song/.prettierrc
nonebot_plugin_guess_song/__init__.py
nonebot_plugin_guess_song/config.py
nonebot_plugin_guess_song/libraries/__init__.py
nonebot_plugin_guess_song/libraries/guess_character.py
nonebot_plugin_guess_song/libraries/guess_cover.py
nonebot_plugin_guess_song/libraries/guess_song_chart.py
nonebot_plugin_guess_song/libraries/guess_song_clue.py
nonebot_plugin_guess_song/libraries/guess_song_listen.py
nonebot_plugin_guess_song/libraries/guess_song_maidle.py
nonebot_plugin_guess_song/libraries/guess_song_note.py
nonebot_plugin_guess_song/libraries/music_model.py
nonebot_plugin_guess_song/libraries/utils.py
nonebot_plugin_guess_song-1.4.0.dist-info/RECORD
