Metadata-Version: 2.1
Name: nonebot-plugin-guess-song
Version: 1.4.0
Summary: A Guess song plugin for Nonebot2
Keywords: nonebot2,plugin,maimaiDX,舞萌DX,guess,song
Author-Email: ssgXD <554700172@qq.com>, sab_tico <3116295766@qq.com>, WAduck <1447671663@qq.com>, qianorange <2080396637@qq.com>
License: MIT
Project-URL: homepage, https://github.com/apshuang/nonebot-plugin-guess-song
Project-URL: repository, https://github.com/apshuang/nonebot-plugin-guess-song
Project-URL: documentation, https://github.com/apshuang/nonebot-plugin-guess-song#readme
Requires-Python: <4.0,>=3.9
Requires-Dist: nonebot2>=2.3.0
Requires-Dist: nonebot-adapter-onebot>=2.3.0
Requires-Dist: nonebot-plugin-apscheduler>=0.5.0
Requires-Dist: nonebot-plugin-localstore>=0.7.0
Requires-Dist: pillow>=11.1.0
Requires-Dist: pydub<0.26.0,>=0.24.1
